plover_dict_commands.py
plover_dict_commands-0.2.5.dist-info/DESCRIPTION.rst
plover_dict_commands-0.2.5.dist-info/METADATA
plover_dict_commands-0.2.5.dist-info/RECORD
plover_dict_commands-0.2.5.dist-info/WHEEL
plover_dict_commands-0.2.5.dist-info/entry_points.txt
plover_dict_commands-0.2.5.dist-info/metadata.json
plover_dict_commands-0.2.5.dist-info/top_level.txt
plover_dict_commands-0.2.5.dist-info/zip-safe
