Metadata-Version: 2.0
Name: plover-dict-commands
Version: 0.2.5
Summary: Dictionaries stack manipulation commands for Plover
Home-page: https://github.com/KoiOates/plover_dict_commands
Author: Ian Cloud
Author-email: ko0oyotl@gmail.com
License: GNU General Public License v2 or later (GPLv2+)
Keywords: plover plover_plugin
Platform: UNKNOWN
Classifier: Development Status :: 4 - Beta
Classifier: Environment :: Plugins
Classifier: Intended Audience :: End Users/Desktop
Classifier: License :: OSI Approved :: GNU General Public License v2 or later (GPLv2+)
Classifier: Operating System :: OS Independent
Classifier: Programming Language :: Python :: 2.7
Classifier: Programming Language :: Python :: 3
Classifier: Programming Language :: Python :: 3.4
Classifier: Programming Language :: Python :: 3.5
Requires-Dist: plover (>=4.0.0.dev1)
